django_overextends-0.4.3.dist-info/DESCRIPTION.rst
django_overextends-0.4.3.dist-info/METADATA
django_overextends-0.4.3.dist-info/metadata.json
django_overextends-0.4.3.dist-info/RECORD
django_overextends-0.4.3.dist-info/top_level.txt
django_overextends-0.4.3.dist-info/WHEEL
overextends/__init__.py
overextends/models.py
overextends/tests.py
overextends/templatetags/__init__.py
overextends/templatetags/overextends_tags.py
test_project/__init__.py
test_project/manage.py
test_project/settings.py
test_project/urls.py
